airflow_metrics/__init__.py
airflow_metrics/airflow_metrics/__init__.py
airflow_metrics/airflow_metrics/datadog_logger.py
airflow_metrics/airflow_metrics/patch_bq.py
airflow_metrics/airflow_metrics/patch_gcs_2_bq.py
airflow_metrics/airflow_metrics/patch_requests.py
airflow_metrics/airflow_metrics/patch_stats.py
airflow_metrics/airflow_metrics/patch_tasks.py
airflow_metrics/airflow_metrics/patch_thread.py
airflow_metrics/utils/__init__.py
airflow_metrics/utils/event_utils.py
airflow_metrics/utils/fn_utils.py
airflow_metrics/utils/hook_utils.py
airflow_metrics-0.1.5.dist-info/LICENSE
airflow_metrics-0.1.5.dist-info/METADATA
airflow_metrics-0.1.5.dist-info/WHEEL
airflow_metrics-0.1.5.dist-info/entry_points.txt
airflow_metrics-0.1.5.dist-info/top_level.txt
airflow_metrics-0.1.5.dist-info/RECORD
