Metadata-Version: 2.1
Name: airflow-metrics
Version: 0.1.5
Summary: Airflow plugin for automatically sending metrics from Airflow to Datadog
Home-page: https://github.com/getsentry/airflow-metrics
Author: zylphrex
Author-email: zylphrex@gmail.com
Maintainer: zylphrex
Maintainer-email: zylphrex@gmail.com
License: UNKNOWN
Keywords: airflow,datadogmetrics,plugin
Platform: MacOS
Platform: Unix
Platform: Windows
Classifier: Development Status :: 3 - Alpha
Classifier: Environment :: Plugins
Classifier: License :: OSI Approved :: Apache Software License
Requires-Dist: datadog (>=0.29.3)
